{
    "name": "Kevin Tolentino",
    "email": "kevin.11.7@outlook.com",
    "phone": "63 (937) 988-1345",
    "location": "Bacoor City, Cavite, 4102",
    "postalCode": "4102",
    "linkedin": "",
    "github": "",
    "website": "",
    "experience": [
        {
            "company": "PuzzleHR",
            "title": "Sr Data Architect",
            "location": "FL, US",
            "start_date": "May 2021",
            "end_date": "Nov 2025"
        },
        {
            "company": "M3 Tech",
            "title": "Senior Data Architect",
            "location": "Montreal, Canada",
            "start_date": "Jan 2018",
            "end_date": "Apr 2021"
        },
        {
            "company": "The BHW Group",
            "title": "Data Engineer",
            "location": "TX, US",
            "start_date": "Aug 2015",
            "end_date": "Dec 2017"
        },
        {
            "company": "Sotatek JSC",
            "title": "Sr. Data Analyst",
            "location": "Hanoi, Vietnam",
            "start_date": "Feb 2013",
            "end_date": "Jul 2015"
        }
    ],
    "education": [
        {
            "degree": "Bachelor of Science in Information Technology",
            "school": "Nanjing University",
            "start_year": "2009",
            "end_year": "2013"
        }
    ]
}